cycy/__init__.py
cycy/__main__.py
cycy/compiler.py
cycy/parser.py
cycy/runtime.py
cycy_runtime-0.2.5.dist-info/METADATA
cycy_runtime-0.2.5.dist-info/WHEEL
cycy_runtime-0.2.5.dist-info/top_level.txt
cycy_runtime-0.2.5.dist-info/RECORD
