Metadata-Version: 2.4
Name: cycy-runtime
Version: 0.2.5
Summary: CyCy：新一代Python全场景运行时
Author: 蔡靖杰
Author-email: 1289270215@qq.com
Keywords: python runtime jit compiler
Classifier: Development Status :: 4 - Beta
Classifier: Programming Language :: Python :: 3
Classifier: Programming Language :: Python :: 3.8
Classifier: Programming Language :: Python :: 3.14
Classifier: Programming Language :: Python :: 3 :: Only
Classifier: Programming Language :: Python :: Implementation :: CPython
Classifier: License :: OSI Approved :: MIT License
Classifier: Operating System :: Microsoft :: Windows
Classifier: Intended Audience :: Developers
Classifier: Topic :: Software Development :: Interpreters
Requires-Python: >=3.8
Requires-Dist: Cython>=3.0.0
Requires-Dist: setuptools>=60.0.0
Dynamic: author
Dynamic: author-email
Dynamic: classifier
Dynamic: description
Dynamic: description-content-type
Dynamic: keywords
Dynamic: requires-dist
Dynamic: requires-python
Dynamic: summary
